qrpy/__init__.py
qrpy/__main__.py
qrpy/decoder.py
qrpy/encoder.py
qrpy-0.1.0.dist-info/LICENSE
qrpy-0.1.0.dist-info/METADATA
qrpy-0.1.0.dist-info/WHEEL
qrpy-0.1.0.dist-info/entry_points.txt
qrpy-0.1.0.dist-info/top_level.txt
qrpy-0.1.0.dist-info/RECORD
