Metadata-Version: 2.1
Name: qrpy
Version: 0.1.0
Summary: Encode and Decode basic QR codes
License: MIT
Project-URL: Homepage, https://github.com/bradenhilton/qrpy
Project-URL: Repository, https://github.com/bradenhilton/qrpy
Keywords: qr,qrcode,encode,decode
Classifier: Environment :: Console
Classifier: License :: OSI Approved :: MIT License
Classifier: Programming Language :: Python :: 3
Classifier: Programming Language :: Python :: 3.8
Classifier: Programming Language :: Python :: 3.9
Classifier: Programming Language :: Python :: 3.10
Classifier: Topic :: Utilities
Requires-Python: >=3.8
License-File: LICENSE
Requires-Dist: Pillow
Requires-Dist: pyzbar
Requires-Dist: qrcode
Provides-Extra: dev
Requires-Dist: mypy ; extra == 'dev'
Requires-Dist: ruff ; extra == 'dev'
Requires-Dist: types-Pillow ; extra == 'dev'
